{
  "name": "overview",
  "luigiConfigFragment": [
    {
      "data": {
        "nodes": [
          {
            "entityType": "main",
            "pathSegment": "accounts",
            "label": "Account List",
            "keepSelectedForChildren": true,
            "icon": "home",
            "url": "https://fiddle.luigi-project.io/examples/microfrontends/multipurpose.html",
            "context": {
              "title": "Welcome to Account List",
              "content": " "
            },
            "children": [
              {
                "pathSegment": ":accountId",
                "hideFromNav": true,
                "keepSelectedForChildren": false,
                "defineEntity": {
                  "id": "account"
                },
                "context": {
                  "accountId": ":accountId"
                }
              }
            ]
          },
          {
            "entityType": "main.account",
            "pathSegment": "overview",
            "label": "Overview",
            "icon": "curriculum",
            "url": "https://fiddle.luigi-project.io/examples/microfrontends/multipurpose.html?acc=:accountId",
            "context": {
              "title": ":accountId",
              "content": " "
            }
          }
        ]
      }
    }
  ]
}